LICENSE
LICENSE.GPL-2
MANIFEST.in
README.md
pyproject.toml
setup.py
version.py
bin/openqa-review-daily-email
bin/openqa-review-functional_yast_concise
bin/openqa-review-sles-ha
openqa_review/__init__.py
openqa_review/browser.py
openqa_review/openqa_review.py
openqa_review/tumblesle_release.py
openqa_review.egg-info/PKG-INFO
openqa_review.egg-info/SOURCES.txt
openqa_review.egg-info/dependency_links.txt
openqa_review.egg-info/entry_points.txt
openqa_review.egg-info/requires.txt
openqa_review.egg-info/top_level.txt