Metadata-Version: 2.1
Name: openqa-review
Version: 1.25.0
Summary: review helper script for openQA
Home-page: https://github.com/os-autoinst/openqa_review
Author: Oliver kurz
Author-email: okurz@suse.com
License: MIT
Keywords: openQA webscraping script helper review
Platform: UNKNOWN
Classifier: Development Status :: 5 - Production/Stable
Classifier: Topic :: Utilities
Classifier: License :: OSI Approved :: MIT License
Classifier: Programming Language :: Python :: 3
License-File: LICENSE.GPL-2
License-File: LICENSE
